istop/__init__.py
istop/model.py
istop/topsis.py
istop-0.0.1.1.dist-info/METADATA
istop-0.0.1.1.dist-info/WHEEL
istop-0.0.1.1.dist-info/top_level.txt
istop-0.0.1.1.dist-info/RECORD
