Metadata-Version: 2.1
Name: istop
Version: 0.0.1.1
Summary: Python implementation of TOPSIS method
Home-page: https://github.com/egemenzeytinci/istop
Author: Egemen Zeytinci
Author-email: egemenzeytinci@gmail.com
Classifier: License :: OSI Approved :: MIT License
Classifier: Programming Language :: Python :: 3.7
Classifier: Programming Language :: Python :: 3.8
Classifier: Programming Language :: Python :: 3.9
Classifier: Programming Language :: Python :: 3.10
Classifier: Operating System :: MacOS
Classifier: Operating System :: POSIX :: Linux
Requires-Dist: numpy
